{
	"user1": {
		"arrangements": {
			"arrangeable": false,
			"dashboard": {},
			"home": {},
			"hvac": {},
			"phone": {},
			"radio": {}
		},
		"climate": {
			"acSelected": false,
			"autoSelected": false,
			"fanSpeed": 0,
			"leftHeat": false,
			"leftTemp": 0,
			"recirculate": false,
			"rightHeat": false,
			"rightTemp": 0
		},
		"colorAccent": "#e0b094",
		"colorHighlight": "#ffffff",
		"components": {
			"welcome": {
				"small1": "heater",
				"small2": "multimedia"
			}
		},
		"fontSize": 0,
		"name": "Laura",
		"skin": "copper",
		"topLocations": [
			{
					"description": "Home",
					"coordinates": {"lat": 37.790416, "lon": -122.396185}
			},
			{
					"description": "Philz coffee",
					"coordinates": {"lat": 37.788920, "lon": -122.393154}
			},
			{
					"description": "School",
					"coordinates": {"lat": 37.793424, "lon": -122.401124}
			},
			{
					"description": "Work",
					"coordinates": {"lat": 37.783902, "lon": -122.396148}
			},
			{
					"description": "MOMA",
					"coordinates": {"lat": 37.785684, "lon": -122.401035}
			}
		]
	},
	"user2": {
		"arrangements": {
			"arrangeable": false,
			"dashboard": {
				"topLeft": "bottom",
				"bottom": "top",
				"top": "topLeft"
			},
			"home": {
				"medium": "tray1",
				"small1": "tray3",
				"small2": "small1",
				"tray1": "tray2",
				"tray2": "medium",
				"tray3": "small2"
			},
			"hvac": {
				"left": "bottom",
				"bottom": "top",
				"top": "left"
			},
			"phone": {
				"left": "bottom",
				"bottom": "left"
			},
			"radio": {
				"left": "topLeft",
				"topLeft": "left",
				"right": "topRight",
				"topRight": "right",
				"bottom": "top",
				"top": "bottom"
			}
		},
		"climate": {
			"acSelected": false,
			"autoSelected": false,
			"fanSpeed": 0,
			"leftHeat": false,
			"leftTemp": 0,
			"recirculate": false,
			"rightHeat": false,
			"rightTemp": 0
		},
		"colorAccent": "#cccccc",
		"colorHighlight": "#566af0",
		"components": {
			"welcome": {
				"small1": "weather",
				"small2": "multimedia"
			}
		},
		"fontSize": 0,
		"name": "Thomas",
		"skin": "titanium",
		"topLocations": [
			{
					"description": "Home",
					"coordinates": {"lat": 37.790416, "lon": -122.396185}
			},
			{
					"description": "Philz coffee",
					"coordinates": {"lat": 37.788920, "lon": -122.393154}
			},
			{
					"description": "School",
					"coordinates": {"lat": 37.793318, "lon": -122.400845}
			},
			{
					"description": "Work",
					"coordinates": {"lat": 37.783902, "lon": -122.396148}
			},
			{
					"description": "MOMA",
					"coordinates": {"lat": 37.785684, "lon": -122.401035}
			}
		]
	}
}
